gae_validators/__init__.py
gae_validators-1.0.4.dist-info/LICENSE
gae_validators-1.0.4.dist-info/WHEEL
gae_validators-1.0.4.dist-info/METADATA
gae_validators-1.0.4.dist-info/RECORD
