Metadata-Version: 2.1
Name: gae-validators
Version: 1.0.4
Summary: User input validation with defaults for the Google App Engine datastore.
Home-page: https://github.com/bdoms/gae_validators
License: MIT
Keywords: validation,google app engine,datastore,forms
Author: Brendan Doms
Author-email: b@bdoms.com
Requires-Python: >=2.7,<4.0
Classifier: License :: OSI Approved :: MIT License
Classifier: Programming Language :: Python :: 2
Classifier: Programming Language :: Python :: 2.7
Classifier: Programming Language :: Python :: 3
Classifier: Programming Language :: Python :: 3.4
Classifier: Programming Language :: Python :: 3.5
Classifier: Programming Language :: Python :: 3.6
Classifier: Programming Language :: Python :: 3.7
Classifier: Programming Language :: Python :: 3.8
Project-URL: Repository, https://github.com/bdoms/gae_validators
